lockup/__init__.py
lockup/exceptions.py
lockup/factories.py
lockup/interception.py
lockup/module.py
lockup/nomenclature.py
lockup/reflection.py
lockup/validators.py
lockup/visibility.py
lockup/exceptionality/__init__.py
lockup/exceptionality/general.py
lockup/exceptionality/our_factories.py
lockup-2.2.0.dist-info/LICENSE.txt
lockup-2.2.0.dist-info/METADATA
lockup-2.2.0.dist-info/WHEEL
lockup-2.2.0.dist-info/top_level.txt
lockup-2.2.0.dist-info/RECORD
