Metadata-Version: 2.1
Name: lockup
Version: 2.2.0
Summary: Immutable and concealed attributes for classes, modules, and namespaces.
Author-email: Eric McDonald <python-lockup@googlegroups.com>
License: Apache-2.0
Project-URL: Homepage, https://github.com/emcd/python-lockup
Project-URL: Documentation, https://emcd.github.io/python-lockup
Project-URL: Source Code, https://github.com/emcd/python-lockup
Project-URL: Download, https://pypi.org/project/lockup/#files
Project-URL: Issue Tracker, https://github.com/emcd/python-lockup/issues
Project-URL: Google Group, https://groups.google.com/g/python-lockup
Keywords: api,attribute,concealment,immutability,namespace
Classifier: Development Status :: 7 - Inactive
Classifier: Intended Audience :: Developers
Classifier: License :: OSI Approved :: Apache Software License
Classifier: Programming Language :: Python :: 3 :: Only
Classifier: Programming Language :: Python :: 3.10
Classifier: Programming Language :: Python :: 3.11
Classifier: Programming Language :: Python :: Implementation :: CPython
Classifier: Programming Language :: Python :: Implementation :: PyPy
Classifier: Topic :: Software Development
Requires-Python: >=3.10
License-File: LICENSE.txt
